InfiniteList/InfiniteList.py
InfiniteList/InfiniteList_versus_list.py
InfiniteList-1.dist-info/LICENSE
InfiniteList-1.dist-info/METADATA
InfiniteList-1.dist-info/WHEEL
InfiniteList-1.dist-info/entry_points.txt
InfiniteList-1.dist-info/top_level.txt
InfiniteList-1.dist-info/RECORD
