Metadata-Version: 2.1
Name: InfiniteList
Version: 1
Summary: This package contains implementation of the library "InfiniteList". InfiniteList is a data type supporting lists of any lengths by using class attributes storing small sublists.
Home-page: https://github.com/GlobalCreativeCommunityFounder/InfiniteList
Author: GlobalCreativeCommunityFounder
Author-email: globalcreativecommunityfounder@gmail.com
License: MIT
Platform: UNKNOWN
Classifier: Programming Language :: Python :: 3
Classifier: Programming Language :: Python :: 3.7
